ncsatranscriptor/__init__.py
ncsatranscriptor/ncsatranscriptor.py
ncsatranscriptor/tests/__init__.py
ncsatranscriptor/tests/test_ncsatranscriptor.py
ncsatranscriptor-0.0.1.dist-info/LICENSE
ncsatranscriptor-0.0.1.dist-info/METADATA
ncsatranscriptor-0.0.1.dist-info/WHEEL
ncsatranscriptor-0.0.1.dist-info/top_level.txt
ncsatranscriptor-0.0.1.dist-info/RECORD
