Metadata-Version: 2.1
Name: ncsatranscriptor
Version: 0.0.1
Summary: A simple string transcriptor for a code interview
Home-page: https://bitbucket.org/uiuc-code/prescreen-transcriptor/
Author: Henry D, Priest
Author-email: Henry Priest <hd.priest@outlook.com>
Project-URL: Homepage, https://bitbucket.org/uiuc-code/prescreen-transcriptor/
Project-URL: Issues, https://bitbucket.org/uiuc-code/prescreen-transcriptor/jira
Classifier: Programming Language :: Python :: 3
Classifier: License :: OSI Approved :: MIT License
Classifier: Operating System :: OS Independent
Requires-Python: >=3.6, <4
License-File: LICENSE
Provides-Extra: dev
Provides-Extra: test
